{
  "program": "veilsub_v8.aleo",
  "version": "0.2.0",
  "description": "VeilSub v8 - Private Creator Subscriptions on Aleo (CreatorReceipts, AuditTokens, Content Integrity)",
  "license": "MIT",
  "leo": "3.4.0",
  "dependencies": [
    {
      "name": "credits.aleo",
      "location": "network",
      "path": null,
      "edition": null
    },
    {
      "name": "token_registry.aleo",
      "location": "network",
      "path": null,
      "edition": null
    }
  ],
  "dev_dependencies": null
}
